Metadata-Version: 1.0
Name: wtf
Version: 0.1
Summary: Post-mortem PDB handler
Home-page: http://github.com/k0001/wtf
Author: Renzo Carbonara
Author-email: gnuk0001@gmail.com
License: BSD
Keywords: pdb debug
Platform: UNKNOWN
Classifier: Development Status :: 4 - Beta
Classifier: Topic :: Software Development :: Debuggers
Classifier: Intended Audience :: Developers
Classifier: License :: OSI Approved :: BSD License
Classifier: Operating System :: OS Independent
Classifier: Programming Language :: Python
